{
  "$comment": "Lista canónica de ciudades-consumidor (capitales del mundo). FUENTE ÚNICA compartida por el seed del backend (backend/src/seed.ts) y el binario bots-ciudad. username = slug de login; population_weight = población metropolitana aproximada en miles, usada como peso para (a) el capital semilla y (b) el reparto del ingreso recurrente (flujo circular). Los valores son aproximados; solo importa su magnitud relativa.",
  "cities": [
    { "username": "tokyo", "display": "Tokyo", "population_weight": 37400 },
    { "username": "delhi", "display": "New Delhi", "population_weight": 32900 },
    { "username": "jakarta", "display": "Jakarta", "population_weight": 33400 },
    { "username": "manila", "display": "Manila", "population_weight": 24900 },
    { "username": "seoul", "display": "Seoul", "population_weight": 25000 },
    { "username": "dhaka", "display": "Dhaka", "population_weight": 23200 },
    { "username": "beijing", "display": "Beijing", "population_weight": 21900 },
    { "username": "cairo", "display": "Cairo", "population_weight": 21900 },
    { "username": "mexico_city", "display": "Mexico City", "population_weight": 21800 },
    { "username": "moscow", "display": "Moscow", "population_weight": 17300 },
    { "username": "bangkok", "display": "Bangkok", "population_weight": 17000 },
    { "username": "kinshasa", "display": "Kinshasa", "population_weight": 15600 },
    { "username": "bogota", "display": "Bogota", "population_weight": 11300 },
    { "username": "paris", "display": "Paris", "population_weight": 11100 },
    { "username": "lima", "display": "Lima", "population_weight": 11000 },
    { "username": "london", "display": "London", "population_weight": 9500 },
    { "username": "tehran", "display": "Tehran", "population_weight": 9500 },
    { "username": "luanda", "display": "Luanda", "population_weight": 8300 },
    { "username": "kuala_lumpur", "display": "Kuala Lumpur", "population_weight": 8200 },
    { "username": "hanoi", "display": "Hanoi", "population_weight": 8100 },
    { "username": "riyadh", "display": "Riyadh", "population_weight": 7700 },
    { "username": "baghdad", "display": "Baghdad", "population_weight": 7600 },
    { "username": "taipei", "display": "Taipei", "population_weight": 7000 },
    { "username": "santiago", "display": "Santiago", "population_weight": 6800 },
    { "username": "madrid", "display": "Madrid", "population_weight": 6700 },
    { "username": "washington", "display": "Washington DC", "population_weight": 6300 },
    { "username": "khartoum", "display": "Khartoum", "population_weight": 6000 },
    { "username": "singapore", "display": "Singapore", "population_weight": 5900 },
    { "username": "ankara", "display": "Ankara", "population_weight": 5700 },
    { "username": "addis_ababa", "display": "Addis Ababa", "population_weight": 5200 },
    { "username": "nairobi", "display": "Nairobi", "population_weight": 5100 },
    { "username": "brasilia", "display": "Brasilia", "population_weight": 4800 },
    { "username": "kabul", "display": "Kabul", "population_weight": 4600 },
    { "username": "rome", "display": "Rome", "population_weight": 4300 },
    { "username": "amman", "display": "Amman", "population_weight": 4000 },
    { "username": "berlin", "display": "Berlin", "population_weight": 3600 },
    { "username": "abuja", "display": "Abuja", "population_weight": 3600 },
    { "username": "warsaw", "display": "Warsaw", "population_weight": 3100 },
    { "username": "kyiv", "display": "Kyiv", "population_weight": 3000 },
    { "username": "vienna", "display": "Vienna", "population_weight": 2900 },
    { "username": "caracas", "display": "Caracas", "population_weight": 2900 },
    { "username": "algiers", "display": "Algiers", "population_weight": 2800 },
    { "username": "accra", "display": "Accra", "population_weight": 2500 },
    { "username": "havana", "display": "Havana", "population_weight": 2100 },
    { "username": "rabat", "display": "Rabat", "population_weight": 1900 },
    { "username": "budapest", "display": "Budapest", "population_weight": 1800 },
    { "username": "bucharest", "display": "Bucharest", "population_weight": 1800 },
    { "username": "ottawa", "display": "Ottawa", "population_weight": 1400 },
    { "username": "islamabad", "display": "Islamabad", "population_weight": 1200 },
    { "username": "reykjavik", "display": "Reykjavik", "population_weight": 240 }
  ]
}
